Metadata-Version: 1.0
Name: nsn-distributions
Version: 1.0
Summary: Gaussian distributions
Home-page: UNKNOWN
Author: Odeyale Kehinde
Author-email: odeyale_kehinde@yahoo.com
License: UNKNOWN
Platform: UNKNOWN
